policyengine_it/__init__.py
policyengine_it/constants.py
policyengine_it/entities.py
policyengine_it/model_api.py
policyengine_it/modelled_policies.yaml
policyengine_it/typing.py
policyengine_it/data/__init__.py
policyengine_it/data/datasets/__init__.py
policyengine_it/data/datasets/country_template_dataset.py
policyengine_it/data/storage/country_template_dataset.h5
policyengine_it/parameters/gov/ade/credits/non_refundable.yaml
policyengine_it/parameters/gov/ade/credits/refundable.yaml
policyengine_it/parameters/gov/ade/credits/dependent_child/eligibility.yaml
policyengine_it/parameters/gov/ade/credits/dependent_child/amount/disabled.yaml
policyengine_it/parameters/gov/ade/credits/dependent_child/amount/standard.yaml
policyengine_it/parameters/gov/ade/credits/dependent_spouse/additional.yaml
policyengine_it/parameters/gov/ade/credits/dependent_spouse/base_amount.yaml
policyengine_it/parameters/gov/ade/credits/dependent_spouse/phase_out.yaml
policyengine_it/parameters/gov/ade/credits/dependent_spouse/eligibility/household_income.yaml
policyengine_it/parameters/gov/ade/credits/dependent_spouse/eligibility/spouse_income.yaml
policyengine_it/parameters/gov/ade/credits/low_income/eligibility.yaml
policyengine_it/parameters/gov/ade/credits/low_income/exemption_rate.yaml
policyengine_it/parameters/gov/ade/tax/income/income_tax_schedule.yaml
policyengine_it/parameters/gov/inps/inclusion_checks/amount.yaml
policyengine_it/parameters/gov/inps/social_security/rates/employee.yaml
policyengine_it/parameters/gov/inps/social_security/rates/executive.yaml
policyengine_it/parameters/gov/inps/social_security/rates/unemployed.yaml
policyengine_it/parameters/gov/inps/universal_credit/base_amount.yaml
policyengine_it/parameters/gov/inps/universal_credit/max_dependent_age.yaml
policyengine_it/parameters/gov/inps/universal_credit/higher/threshold.yaml
policyengine_it/parameters/gov/inps/universal_credit/standard/age_factor.yaml
policyengine_italy-0.16.0.dist-info/LICENSE
policyengine_italy-0.16.0.dist-info/METADATA
policyengine_italy-0.16.0.dist-info/WHEEL
policyengine_italy-0.16.0.dist-info/top_level.txt
policyengine_italy-0.16.0.dist-info/RECORD
