Metadata-Version: 2.1
Name: policyengine-italy
Version: 0.16.0
Summary: Microsimulation model for Italy's tax-benefit system.
Home-page: https://github.com/policyengine/policyengine-italy
Author: PolicyEngine
Author-email: hello@policyengine.org
License: https://www.fsf.org/licensing/licenses/agpl-3.0.html
Keywords: tax benefit microsimulation framework
Platform: UNKNOWN
Classifier: Development Status :: 2 - Pre-Alpha
Classifier: License :: OSI Approved :: GNU Affero General Public License v3
Classifier: Operating System :: POSIX
Classifier: Programming Language :: Python
Classifier: Programming Language :: Python :: 3.7
Classifier: Programming Language :: Python :: 3.8
Classifier: Programming Language :: Python :: 3.9
Classifier: Programming Language :: Python :: 3.10
Classifier: Topic :: Scientific/Engineering :: Information Analysis
Requires-Python: >=3.7
License-File: LICENSE
Requires-Dist: black[jupyter]
Requires-Dist: coverage <7
Requires-Dist: dpath <3
Requires-Dist: h5py <4,>=3
Requires-Dist: linecheck <1
Requires-Dist: microdf-python <1,>=0.3.0
Requires-Dist: nptyping <2
Requires-Dist: numexpr <3
Requires-Dist: pandas <2,>=1.4.2
Requires-Dist: plotly <6,>=5.6.0
Requires-Dist: policyengine-core <3,>=2.16
Requires-Dist: psutil <6
Requires-Dist: pytest
Requires-Dist: requests <3,>=2.27.1
Requires-Dist: sortedcontainers <3
Requires-Dist: tqdm <5,>=4.46.0
Requires-Dist: wheel <1
Requires-Dist: yaml-changelog ==0.3.0
Provides-Extra: dev
Requires-Dist: furo ; extra == 'dev'
Requires-Dist: jupyter-book ; extra == 'dev'
Requires-Dist: markupsafe ; extra == 'dev'
Requires-Dist: pydata-sphinx-theme ; extra == 'dev'
Requires-Dist: sphinx ; extra == 'dev'
Requires-Dist: sphinx-argparse ; extra == 'dev'
Requires-Dist: sphinx-math-dollar ; extra == 'dev'
